{"cameraMode":{"drawMode":0,"name":"Shaded","section":"Shading Mode"},"sceneLighting":false,"audioPlay":false,"sceneViewState":{"m_AlwaysRefresh":false,"showFog":true,"showSkybox":false,"showFlares":true,"showImageEffects":true,"showParticleSystems":true,"showVisualEffectGraphs":true,"m_FxEnabled":true},"in2DMode":false,"pivot":{"x":-1.6206140518188477,"y":-0.0551074743270874,"z":-0.9531149864196777},"rotation":{"x":0.016927316784858705,"y":-0.9728931784629822,"z":0.2180686742067337,"w":0.0754563957452774},"size":1.8022602796554566,"orthographic":false}